README.md
setup.py
zeahoDateUtil/__init__.py
zeahoDateUtil/parse_datetime.py
zeahoDateUtil.egg-info/PKG-INFO
zeahoDateUtil.egg-info/SOURCES.txt
zeahoDateUtil.egg-info/dependency_links.txt
zeahoDateUtil.egg-info/not-zip-safe
zeahoDateUtil.egg-info/requires.txt
zeahoDateUtil.egg-info/top_level.txt